PythonSafeEval/Dockerfile_template.txt
PythonSafeEval/__init__.py
PythonSafeEval/safe_eval.py
PythonSafeEval-0.0.1.dist-info/LICENSE
PythonSafeEval-0.0.1.dist-info/METADATA
PythonSafeEval-0.0.1.dist-info/WHEEL
PythonSafeEval-0.0.1.dist-info/top_level.txt
PythonSafeEval-0.0.1.dist-info/RECORD
