Metadata-Version: 2.1
Name: PythonSafeEval
Version: 0.0.1
Summary: Safely execute arbitrary Python codes using nsjail.
Home-page: https://github.com/s3131212/PythonSafeEval
Author: Allen Chou
Author-email: s3131212@gmail.com
License: MIT License
Platform: UNKNOWN
Requires-Python: >=3.6
